aioautobatch/__init__.py
aioautobatch-0.1.4.dist-info/METADATA
aioautobatch-0.1.4.dist-info/WHEEL
aioautobatch-0.1.4.dist-info/top_level.txt
aioautobatch-0.1.4.dist-info/RECORD
