Metadata-Version: 2.4
Name: aioautobatch
Version: 0.1.4
Summary: Add your description here
Requires-Python: >=3.11
